auto_notifier/__init__.py
auto_notifier/core.py
auto_notifier-0.1.0.dist-info/METADATA
auto_notifier-0.1.0.dist-info/WHEEL
auto_notifier-0.1.0.dist-info/licenses/LICENSE
auto_notifier-0.1.0.dist-info/RECORD
