Metadata-Version: 2.4
Name: auto-notifier
Version: 0.1.0
Summary: Decorator and context manager for desktop notifications when Python jobs finish.
Project-URL: Homepage, https://github.com/yalmeidarj/auto-notifier
Project-URL: Issues, https://github.com/yalmeidarj/auto-notifier
Author-email: Yuri Almeida <yalmeida.rj@gmail.com>
License: MIT
License-File: LICENSE
Keywords: context manager,decorator,desktop,long-running,notifications
Classifier: License :: OSI Approved :: GNU General Public License v3 (GPLv3)
Classifier: Operating System :: OS Independent
Classifier: Programming Language :: Python :: 3
Classifier: Typing :: Typed
Requires-Python: >=3.8
Requires-Dist: notify-py>=0.3.0
